libcmd/__init__.py
libcmd-3.0.dist-info/METADATA
libcmd-3.0.dist-info/WHEEL
libcmd-3.0.dist-info/top_level.txt
libcmd-3.0.dist-info/RECORD
